yourtube/YourTube.ipynb
yourtube/__init__.py
yourtube/anti_clickbait.ipynb
yourtube/debug.ipynb
yourtube/file_operations.py
yourtube/junkyard/YourTube_unused_ideas_dump.ipynb
yourtube/junkyard/_HCS.ipynb
yourtube/junkyard/_louvain.ipynb
yourtube/scraping.py
yourtube-0.7.0.dist-info/entry_points.txt
yourtube-0.7.0.dist-info/LICENSE
yourtube-0.7.0.dist-info/WHEEL
yourtube-0.7.0.dist-info/METADATA
yourtube-0.7.0.dist-info/RECORD
