Metadata-Version: 2.1
Name: yourtube
Version: 0.7.0
Summary: Better youtube recommendations
License: LGPL-2.1
Author: Filip Sondej
Author-email: filipsondej@protonmail.com
Requires-Python: >=3.8,<3.10
Classifier: License :: OSI Approved
Classifier: Programming Language :: Python :: 3
Classifier: Programming Language :: Python :: 3.8
Classifier: Programming Language :: Python :: 3.9
Requires-Dist: ipyvuetify (>=1.8.1,<2.0.0)
Requires-Dist: ipywidgets (>=7.6.3,<8.0.0)
Requires-Dist: krakow (>=0.1.2,<0.2.0)
Requires-Dist: magic-wormhole (>=0.12.0,<0.13.0)
Requires-Dist: matplotlib (>=3.4.2,<4.0.0)
Requires-Dist: networkx (>=2.6.1,<3.0.0)
Requires-Dist: numpy (>=1.21.0,<2.0.0)
Requires-Dist: pickleDB (>=0.9.2,<0.10.0)
Requires-Dist: python-dateutil (>=2.8.2,<3.0.0)
Requires-Dist: requests (>=2.26.0,<3.0.0)
Requires-Dist: scipy (>=1.7.0,<2.0.0)
Requires-Dist: sklearn (>=0.0,<0.1)
Requires-Dist: tqdm (>=4.61.2,<5.0.0)
Requires-Dist: voila (>=0.2.10,<0.3.0)
Requires-Dist: youtube-transcript-api (>=0.4.1,<0.5.0)
